setup.py
surrogate_set_imputer/surrogate_set_imputer.py
surrogate_set_imputer.egg-info/PKG-INFO
surrogate_set_imputer.egg-info/SOURCES.txt
surrogate_set_imputer.egg-info/dependency_links.txt
surrogate_set_imputer.egg-info/requires.txt
surrogate_set_imputer.egg-info/top_level.txt